sandiaspecutils-0.0.9.dist-info/WHEEL
sandiaspecutils-0.0.9.dist-info/METADATA
sandiaspecutils-0.0.9.dist-info/RECORD
SpecUtils/SpecUtils.cpython-310-x86_64-linux-gnu.so
SpecUtils/__init__.py
