Metadata-Version: 2.1
Name: SandiaSpecUtils
Version: 0.0.9
Summary: Python bindings for SpecUtils using nanobind and scikit-build
Author-Email: Will Johnson <wcjohns@sandia.gov>
Classifier: License :: OSI Approved :: GNU Lesser General Public License v2 (LGPLv2)
Project-URL: Homepage, https://github.com/sandialabs/SpecUtils
Requires-Python: >=3.9
